sniff/__init__.py
sniff/datatuple.py
snif-0.0.1.dist-info/LICENSE
snif-0.0.1.dist-info/METADATA
snif-0.0.1.dist-info/WHEEL
snif-0.0.1.dist-info/top_level.txt
snif-0.0.1.dist-info/RECORD
