Metadata-Version: 2.1
Name: snif
Version: 0.0.1
Summary: Sensor Networking Interchange Framework
Author: OpenLX
Project-URL: Homepage, https://github.com/inventthings/snif
Project-URL: Bug Tracker, https://github.com/inventthings/snif/issues
Classifier: Programming Language :: Python :: 3
Classifier: Operating System :: OS Independent
Requires-Python: >=3.5
License-File: LICENSE
